{
  "schema": "maeuknam_decision_structure.v1",
  "id": "94bfNuTXCdA",
  "title": "[2025.12.30] 비트코인 분석 #비트코인실시간방송",
  "url": "https://www.youtube.com/watch?v=94bfNuTXCdA",
  "duration": 5242.020875,
  "model": "tiny",
  "bias": {
    "primary_bias": "LONG",
    "long_score": 34,
    "short_score": 11,
    "explanation": "롱/상승/반등 계열 표현이 숏/하락 표현보다 뚜렷하게 많습니다."
  },
  "trade_readiness": {
    "level": "CONDITIONAL",
    "score": 4,
    "reason": "일부 조건은 잡히지만 빠진 축이 있어 차트 프레임 확인 후 규칙화해야 합니다."
  },
  "category_hits": {
    "market_context": 11,
    "direction_judgment": 23,
    "chart_structure": 49,
    "entry_trigger": 29,
    "stop_invalidation": 0,
    "take_profit_exit": 1,
    "timeframe": 5,
    "wave_position": 11
  },
  "sections": {
    "market_context": {
      "hits": 11,
      "summary": "시장 배경 언급이 11회 잡혔고, 대표 구간은 '비트코인의 장기 좀 내셨동으로 추세를 겨우고 채널을 뚫렀지'입니다.",
      "evidence": [
        {
          "time": "00:29:53",
          "start": 1793.04,
          "score": 2,
          "text": "이 평소는 누가 봐도 다 그런 거고 어디 간다 깔 수 있고. 그런데 비트코인 또 이제 이 평소으로"
        },
        {
          "time": "00:37:48",
          "start": 2268.8,
          "score": 4,
          "text": "비트코인의 장기 좀 내셨동으로 추세를 겨우고 채널을 뚫렀지"
        },
        {
          "time": "01:09:27",
          "start": 4167.06,
          "score": 2,
          "text": "엉라면 비티쉬 5만 달러 탁가 내려가는 관점은 어떤가요 지금은 별로 살 등하게 없어요 대체 어떻게 해석하면 5만 달러까지까지"
        },
        {
          "time": "01:10:47",
          "start": 4247.15,
          "score": 2,
          "text": "지금 이제 20점에서 이번 사이크를 해서 처음으로 이탭은 승인이 낙고 기관 자금이 들어오고 있고"
        },
        {
          "time": "01:13:25",
          "start": 4405.1,
          "score": 2,
          "text": "그죠? 기관이 들어오면서 그리고 기관이 다 매이블 했었을 때"
        },
        {
          "time": "01:14:26",
          "start": 4466.51,
          "score": 3,
          "text": "한 번 민시키 모델로 봤을 때도 막고 제가 이야기했던 비트코인 파동관점에서 대단히 분석했었을 때"
        }
      ]
    },
    "direction_judgment": {
      "hits": 23,
      "summary": "방향 판단 언급이 23회 잡혔습니다. 핵심은 '쭉쭉쭉 지지를 받으면서 올라가다가 첫 조정에 왔었을 때 반등하고 두 분째 조정 왔었을 때 반등하고' 구간입니다.",
      "evidence": [
        {
          "time": "00:23:37",
          "start": 1417.9,
          "score": 7,
          "text": "반등이 와서 쓸 때 그러면 어디까지 올 것이냐. 여기가 단기 접점이고 반등이 오면 단기 반등만 오고 대처 하락할 것이냐."
        },
        {
          "time": "00:24:42",
          "start": 1482.54,
          "score": 5,
          "text": "반등에 올라갈지 모르겠지만 어쨌든 여기가 리딩이 나왔기 때문에 곧점돌파을 한 번에 못한다"
        },
        {
          "time": "00:26:08",
          "start": 1568.94,
          "score": 4,
          "text": "AVC 반등에 이어질 수도 있기 때문에 지금에서는 판단 불가능하고 앞으로 나오는 상승파동을 보고"
        },
        {
          "time": "00:32:38",
          "start": 1958.73,
          "score": 8,
          "text": "쭉쭉쭉 지지를 받으면서 올라가다가 첫 조정에 왔었을 때 반등하고 두 분째 조정 왔었을 때 반등하고"
        },
        {
          "time": "00:33:12",
          "start": 1992.13,
          "score": 5,
          "text": "그래서 이번에 만약에 반등이 온다면 반등이 온다고 하더라도 여기에서 저항을 받는지 아니면"
        },
        {
          "time": "00:37:29",
          "start": 2249.68,
          "score": 5,
          "text": "고점에서 추세가 부딪혔을 때 마다 큰 하락이 큰 하락이 큰 하락이 나왔으니까"
        }
      ]
    },
    "chart_structure": {
      "hits": 49,
      "summary": "고점/저점, 지지/저항, 채널/라인 같은 구조 판단이 49회 잡혔습니다.",
      "evidence": [
        {
          "time": "00:17:55",
          "start": 1075.97,
          "score": 9,
          "text": "이제 추세를 좀 그거볼 수가 있어요. 곧점 곧점 이어서 추세를 그다 보면 이런 추세가 그렇고 상단 저항을"
        },
        {
          "time": "00:18:02",
          "start": 1082.53,
          "score": 9,
          "text": "이런 추세가 그렇고 상단 저항을 컨트롤 수 큰퇴 부위에서 하단에 갔다 되면 하단 추세도 이렇게 대략 조금만 보호했습니다."
        },
        {
          "time": "00:21:57",
          "start": 1317.87,
          "score": 6,
          "text": "아직 채널은 끝나지 않은 것 같아요. 아직 채널은 끝나지 않은 것 같고 이더리에 오면 아직 이 하이라그 채널을 소개해 있어 보이는데"
        },
        {
          "time": "00:32:38",
          "start": 1958.73,
          "score": 6,
          "text": "쭉쭉쭉 지지를 받으면서 올라가다가 첫 조정에 왔었을 때 반등하고 두 분째 조정 왔었을 때 반등하고"
        },
        {
          "time": "00:48:31",
          "start": 2911.17,
          "score": 6,
          "text": "엄청 이들도 아니고 양쪽 하나 계속 하겠어. 그래서 환유를 보실 때는 이 상단 저항과 하단지지 사이에서"
        },
        {
          "time": "01:00:20",
          "start": 3620.85,
          "score": 7,
          "text": "고점 넘길 거라고 이야기 했고 고점을 넘겨 쓸 때가 진짜하죠 4,500,000을 뚫지 못하고 조정을 받으면 그 조정이 단기가 아니라 3,800가 제가 하는 큰 조정이 됐고에요"
        }
      ]
    },
    "entry_trigger": {
      "hits": 29,
      "summary": "진입 조건은 추격보다 확인, 눌림, 반등, 돌파 여부 중심으로 29회 등장합니다.",
      "evidence": [
        {
          "time": "00:20:27",
          "start": 1227.28,
          "score": 7,
          "text": "매수 기회는 한 7만 6천 부터 7만 라인까지죠. 이정도가 사실 좋은 가격대기인데 이 자리는 너무 좋은 자리랑 안 줄 것 같아요."
        },
        {
          "time": "00:23:37",
          "start": 1417.9,
          "score": 6,
          "text": "반등이 와서 쓸 때 그러면 어디까지 올 것이냐. 여기가 단기 접점이고 반등이 오면 단기 반등만 오고 대처 하락할 것이냐."
        },
        {
          "time": "00:27:01",
          "start": 1621.18,
          "score": 5,
          "text": "반등이 나왔었을 때 저항이 얼마나 구간을 알려드릴게요. 좋아요 좀 받고 오랜만에"
        },
        {
          "time": "00:32:38",
          "start": 1958.73,
          "score": 7,
          "text": "쭉쭉쭉 지지를 받으면서 올라가다가 첫 조정에 왔었을 때 반등하고 두 분째 조정 왔었을 때 반등하고"
        },
        {
          "time": "00:33:12",
          "start": 1992.13,
          "score": 5,
          "text": "그래서 이번에 만약에 반등이 온다면 반등이 온다고 하더라도 여기에서 저항을 받는지 아니면"
        },
        {
          "time": "01:03:13",
          "start": 3793.94,
          "score": 8,
          "text": "50달라 개꿀 매수자리입니다 개꿀 매수자리인데"
        }
      ]
    },
    "stop_invalidation": {
      "hits": 0,
      "summary": "명확한 근거 구간이 부족합니다.",
      "evidence": []
    },
    "take_profit_exit": {
      "hits": 1,
      "summary": "수익 실현/청산 언급이 1회 잡혔습니다. 목표 도달 후 분할 또는 정리 맥락을 확인해야 합니다.",
      "evidence": [
        {
          "time": "00:57:10",
          "start": 3430.43,
          "score": 3,
          "text": "항상 비트 코인 가격과 스테이티지 뭐 비트마이네. 이더리움에 가격에 매칭해서 같이 올라가면"
        }
      ]
    },
    "timeframe": {
      "hits": 5,
      "summary": "분봉/시간봉/일봉 등 시간 프레임 언급이 5회 잡혔습니다.",
      "evidence": [
        {
          "time": "00:13:10",
          "start": 790.3,
          "score": 3,
          "text": "그다음에 모분봉키고 단타칭다 이것만 대할때 하는 거지 나머지는 똑같아요. 차트 분석하는 거랑 시들아"
        },
        {
          "time": "00:23:37",
          "start": 1417.9,
          "score": 5,
          "text": "반등이 와서 쓸 때 그러면 어디까지 올 것이냐. 여기가 단기 접점이고 반등이 오면 단기 반등만 오고 대처 하락할 것이냐."
        },
        {
          "time": "00:28:56",
          "start": 1736.64,
          "score": 4,
          "text": "1번 상 봤었을 때 1번 차트에요. 그리고 1번이나 주봉차트볼 때는"
        },
        {
          "time": "00:37:48",
          "start": 2268.8,
          "score": 4,
          "text": "비트코인의 장기 좀 내셨동으로 추세를 겨우고 채널을 뚫렀지"
        },
        {
          "time": "01:00:20",
          "start": 3620.85,
          "score": 6,
          "text": "고점 넘길 거라고 이야기 했고 고점을 넘겨 쓸 때가 진짜하죠 4,500,000을 뚫지 못하고 조정을 받으면 그 조정이 단기가 아니라 3,800가 제가 하는 큰 조정이 됐고에요"
        }
      ]
    },
    "wave_position": {
      "hits": 11,
      "summary": "파동/조정 위치 언급이 11회 잡혔습니다. 방향보다 현재 파동 위치 해석이 중요합니다.",
      "evidence": [
        {
          "time": "00:24:35",
          "start": 1475.98,
          "score": 5,
          "text": "복합조정이 뭔가 더 행보로 나와서 이 행보전체를 2파로 보거나 비파으로 보고 반등에 올라갈지 모르겠지만 어쨌든"
        },
        {
          "time": "00:26:08",
          "start": 1568.94,
          "score": 3,
          "text": "AVC 반등에 이어질 수도 있기 때문에 지금에서는 판단 불가능하고 앞으로 나오는 상승파동을 보고"
        },
        {
          "time": "00:32:38",
          "start": 1958.73,
          "score": 7,
          "text": "쭉쭉쭉 지지를 받으면서 올라가다가 첫 조정에 왔었을 때 반등하고 두 분째 조정 왔었을 때 반등하고"
        },
        {
          "time": "00:59:55",
          "start": 3595.57,
          "score": 4,
          "text": "한 4,500까지 목가 그리고 조정이 오면 조정이 오면 일본상 하다가 승리기 때문에"
        },
        {
          "time": "01:00:20",
          "start": 3620.85,
          "score": 8,
          "text": "고점 넘길 거라고 이야기 했고 고점을 넘겨 쓸 때가 진짜하죠 4,500,000을 뚫지 못하고 조정을 받으면 그 조정이 단기가 아니라 3,800가 제가 하는 큰 조정이 됐고에요"
        },
        {
          "time": "01:14:17",
          "start": 4457.47,
          "score": 4,
          "text": "이 쌀클서 기간 처음 들어왔어요 기간 들어오고 첫 조정입니다 다음 조정은 다음 상승 크게 갈 거예요"
        }
      ]
    }
  },
  "scenario_plan": {
    "entry_if": "지지/채널/저점 구조가 유지되고 눌림 후 반등 확인이 나올 때만 롱 후보로 본다.",
    "invalidated_if": "저점 또는 채널 하단이 깨지고 회복하지 못하면 롱 시나리오를 폐기한다.",
    "stop_logic": "손절 근거가 부족하므로 별도 차트 검증 없이는 진입하지 않는다.",
    "target_logic": "직접적인 익절 언급은 약하므로 파동 목표와 다음 구조선을 임시 목표로만 쓰고, 별도 차트 검증 전에는 거래하지 않는다.",
    "avoid_if": "손절 거리가 멀거나, 구조 확인 없이 단어 하나만으로 방향을 정해야 하는 구간은 피한다."
  },
  "algorithm_rules": [
    {
      "name": "structure_first",
      "rule": "방향 신호보다 지지/저항/채널/고점저점 구조 확인을 우선한다.",
      "reason": "차트 구조 히트 49회"
    },
    {
      "name": "stop_before_entry",
      "rule": "진입 전에 손절/무효화 가격을 먼저 계산하고, 손절 폭이 크면 거래하지 않는다.",
      "reason": "손절/무효화 히트 0회"
    },
    {
      "name": "conditional_aggression",
      "rule": "공격적 진입은 구조, 진입조건, 손절조건이 동시에 잡힌 ACTIONABLE 영상 패턴에서만 허용한다.",
      "reason": "현재 판정 CONDITIONAL"
    },
    {
      "name": "direction_bias",
      "rule": "이 영상은 LONG 우위 시나리오로 분류하되, 반대 구조 돌파/이탈 시 즉시 폐기한다.",
      "reason": "long=34, short=11"
    },
    {
      "name": "wave_filter",
      "rule": "파동 위치가 조정 중인지, 3파/5파 진행 중인지 확인한 뒤 진입 방향을 확정한다.",
      "reason": "파동/조정 히트 11회"
    }
  ],
  "quality_flags": [
    "손절/무효화 조건 근거가 부족합니다."
  ]
}