{
  "schema": "maeuknam_decision_structure.v1",
  "id": "RfcXbSuwOuc",
  "title": "[2022.07.30]매억남_비트코인 분석방송 #비트코인 #bitcoin #btc #chart analysis",
  "url": "https://www.youtube.com/watch?v=RfcXbSuwOuc",
  "duration": 5207.1445,
  "model": "tiny",
  "bias": {
    "primary_bias": "LONG",
    "long_score": 28,
    "short_score": 4,
    "explanation": "롱/상승/반등 계열 표현이 숏/하락 표현보다 뚜렷하게 많습니다."
  },
  "trade_readiness": {
    "level": "ACTIONABLE",
    "score": 5,
    "reason": "구조, 진입, 손절이 함께 잡혀 있고 청산 또는 파동 필터까지 있어 실전 규칙 후보로 볼 수 있습니다."
  },
  "category_hits": {
    "market_context": 5,
    "direction_judgment": 18,
    "chart_structure": 15,
    "entry_trigger": 30,
    "stop_invalidation": 3,
    "take_profit_exit": 14,
    "timeframe": 0,
    "wave_position": 34
  },
  "sections": {
    "market_context": {
      "hits": 5,
      "summary": "시장 배경 언급이 5회 잡혔고, 대표 구간은 '아 이제 비트코인 다 오는 것 같다 이제 여기서 제가 제가 대게 빨리 매도를 쳤어요 알트들 다'입니다.",
      "evidence": [
        {
          "time": "01:08:08",
          "start": 4088.08,
          "score": 1,
          "text": "올라가는 거 보니까 지금이 바닥이라고 생각을 하는 거 한테 시장 참여자들이"
        },
        {
          "time": "01:09:32",
          "start": 4172.4,
          "score": 1,
          "text": "75p가 상대적으로 나온 곳은 75p 인상을 진짜 많이 올리는 거예요 역대적으로 가고 역사 보셨 75p 인상은 적 있나? 이렇게 급증적으로 금리 올리"
        },
        {
          "time": "01:11:57",
          "start": 4317.76,
          "score": 3,
          "text": "아 이제 비트코인 다 오는 것 같다 이제 여기서 제가 제가 대게 빨리 매도를 쳤어요 알트들 다"
        },
        {
          "time": "01:12:19",
          "start": 4339.76,
          "score": 2,
          "text": "시장이 근데 이거를 첫 첫 사이받는 분들이 많더라고요 내 형남 분위기 좋은데 시장이 참을 끼운 줬다"
        }
      ]
    },
    "direction_judgment": {
      "hits": 18,
      "summary": "방향 판단 언급이 18회 잡혔습니다. 핵심은 '둘 중에 하나인데 ABC 반등 후 하락하거나 인퍼스 찐반등 후 조정 후 다시 상승하거나' 구간입니다.",
      "evidence": [
        {
          "time": "00:15:40",
          "start": 940.82,
          "score": 6,
          "text": "근데 이 자리에서 아마 매수를 제 방송을 좀 보고 공부를 하셨던 분들은 아마 이 자리에서 롱 매수를 들어 가셨을 거예요."
        },
        {
          "time": "00:21:17",
          "start": 1277.6,
          "score": 7,
          "text": "둘 중에 하나인데 ABC 반등 후 하락하거나 인퍼스 찐반등 후 조정 후 다시 상승하거나"
        },
        {
          "time": "00:22:31",
          "start": 1351.52,
          "score": 3,
          "text": "많이 올라가서 쓸 때는 오히려 손절을 쳐야 되기 때문에 공통 구간에서 반입 줄을 하는 게"
        },
        {
          "time": "00:56:12",
          "start": 3372.71,
          "score": 4,
          "text": "롱매수에서 잘 버렸겠다 여기 보시면 하락 주세요 딱 한 번 크게 막고"
        },
        {
          "time": "01:02:03",
          "start": 3723.22,
          "score": 4,
          "text": "보는 경우가 차라리 이번엔 비트가 맘을 때가 비어에서 들어 돌아가는 게 어차피 롱을 볼 거면 이더런보다 비트롱이 유리하지 않을까요? 이번에는"
        },
        {
          "time": "01:07:06",
          "start": 4026.04,
          "score": 4,
          "text": "차라리 충분히 여기서 조정을 거쳐놓고 뚜롱해서 여기쯤 저기쯤에, 그 차트 지저분하게 나오지"
        }
      ]
    },
    "chart_structure": {
      "hits": 15,
      "summary": "고점/저점, 지지/저항, 채널/라인 같은 구조 판단이 15회 잡혔습니다.",
      "evidence": [
        {
          "time": "00:15:47",
          "start": 947.14,
          "score": 6,
          "text": "아마 이 자리에서 롱 매수를 들어 가셨을 거예요. 너무나 당연하게 트렌드라니 딱 딱 보여서 손이 비가 너무 좋은 하단 지지 부분이었는 데다가"
        },
        {
          "time": "00:39:22",
          "start": 2362.17,
          "score": 8,
          "text": "이렇게 채널은 위에 저항 같다 내가 밑에 밑에 지지 같다 되니까 채널을 보이는 것 같긴 한데"
        },
        {
          "time": "00:40:33",
          "start": 2433.16,
          "score": 4,
          "text": "인퍼를 수가 아니고 기계 조정 와서 다시 채널 이 하단북가 또 아이스를 겨울아가면 여기에 다시 부딪치러 오는 굉장히 높아요"
        },
        {
          "time": "00:54:58",
          "start": 3298.12,
          "score": 6,
          "text": "2018년도 리플 고점은 여기에에요 비트 코엔 고점이 이만 달라고 되니요 근데 지금 비트 코엔 고점이 이만 달라는 거"
        },
        {
          "time": "01:08:46",
          "start": 4126.88,
          "score": 4,
          "text": "고점에서 나오는 호재는 호재가 아니라 악증이라고 바닥에서 포드 나올 때가 살 때고 고점에서"
        },
        {
          "time": "01:15:21",
          "start": 4521.78,
          "score": 4,
          "text": "최고점 찍었을 때 11월 가격 볼게요 11월 가격 여기에요"
        }
      ]
    },
    "entry_trigger": {
      "hits": 30,
      "summary": "진입 조건은 추격보다 확인, 눌림, 반등, 돌파 여부 중심으로 30회 등장합니다.",
      "evidence": [
        {
          "time": "00:15:40",
          "start": 940.82,
          "score": 9,
          "text": "근데 이 자리에서 아마 매수를 제 방송을 좀 보고 공부를 하셨던 분들은 아마 이 자리에서 롱 매수를 들어 가셨을 거예요."
        },
        {
          "time": "00:18:32",
          "start": 1112.34,
          "score": 6,
          "text": "늦게 하지만 그 반 매수 좋은 자리에서 들어 한 건 잘 하셨는데 여기 뻔히 보이는 반입절 자리였잖아."
        },
        {
          "time": "00:21:17",
          "start": 1277.6,
          "score": 5,
          "text": "둘 중에 하나인데 ABC 반등 후 하락하거나 인퍼스 찐반등 후 조정 후 다시 상승하거나"
        },
        {
          "time": "00:29:18",
          "start": 1758.03,
          "score": 4,
          "text": "확인차 확인차 잘 받으셨나 확인 날려고 하는 거 설마 조다가 뺄겠습니까 이건 이제 차트 분석으로 넘어 와서"
        },
        {
          "time": "00:35:42",
          "start": 2142.39,
          "score": 7,
          "text": "그러면 이 자리구 6개파 자리가 또 마침 늘 공교롭게도 4파 조정이 있었던 맴을 때 자리에요"
        },
        {
          "time": "01:25:37",
          "start": 5137.75,
          "score": 5,
          "text": "무작정 여기 무시성을 아는 거 들어가자고 또는 진파던 보고 들어가임만 자리 있으면 들어가으면"
        }
      ]
    },
    "stop_invalidation": {
      "hits": 3,
      "summary": "손절/무효화 언급이 3회 잡혔습니다. 진입 전 리스크 위치를 먼저 보는 영상입니다.",
      "evidence": [
        {
          "time": "00:22:29",
          "start": 1349.92,
          "score": 3,
          "text": "여기에 반입 줄을 때리는 게 공통 구간이 있고 많이 올라가서 쓸 때는 오히려 손절을 쳐야 되기 때문에"
        },
        {
          "time": "00:22:31",
          "start": 1351.52,
          "score": 3,
          "text": "많이 올라가서 쓸 때는 오히려 손절을 쳐야 되기 때문에 공통 구간에서 반입 줄을 하는 게"
        },
        {
          "time": "00:44:02",
          "start": 2642.04,
          "score": 3,
          "text": "한쪽을 좀 일단 롱근 여기서 타다고 여기 있다 여보여 중요한 거 이거 보고 판단에 가면 손절을 칭니다"
        },
        {
          "time": "01:14:12",
          "start": 4452.72,
          "score": 4,
          "text": "명남 틀렸네 이때 손절하지 말걸 이때 손절하지 말걸"
        }
      ]
    },
    "take_profit_exit": {
      "hits": 14,
      "summary": "수익 실현/청산 언급이 14회 잡혔습니다. 목표 도달 후 분할 또는 정리 맥락을 확인해야 합니다.",
      "evidence": [
        {
          "time": "00:15:04",
          "start": 904.93,
          "score": 5,
          "text": "외치 하다내서 나오는 구간에서 로웅을 타서 반등 나오는 반익절을 때리고 나머지 호딩을 해서 떨어지면 본적으로 치고 올라가면 호딩을 하자"
        },
        {
          "time": "00:17:44",
          "start": 1064.21,
          "score": 6,
          "text": "있어가지고 아니 청산이 재밌게 아니 청산 남이 청산당했다고 재밌다는 게 아니라"
        },
        {
          "time": "00:19:26",
          "start": 1166.62,
          "score": 3,
          "text": "할까 싶고 여기 단타를 차선이 그런 수익이 있었고 어디 구간 한 번도 수익이 있어서"
        },
        {
          "time": "00:20:52",
          "start": 1252.32,
          "score": 3,
          "text": "둘 다 여기도 상감 없다. 어차피 이건 무조건 공통 구간 쇼구간에서 수익을 가져간다."
        },
        {
          "time": "00:22:18",
          "start": 1338.16,
          "score": 4,
          "text": "380 끝나고 나오는 480 조정 후가 아니을 거잖아요. 그래서 480 조정에도 수익이 있고 그다음에 떨어진 ABC 반등 후"
        },
        {
          "time": "00:23:17",
          "start": 1397.71,
          "score": 3,
          "text": "그다음에 또 다시 아까 말씀드렸던 단타 구간에서 공통 구간에서 맨날 쳐서 수익이 나서"
        }
      ]
    },
    "timeframe": {
      "hits": 0,
      "summary": "분봉/시간봉/일봉 등 시간 프레임 언급이 0회 잡혔습니다.",
      "evidence": [
        {
          "time": "00:46:39",
          "start": 2799.33,
          "score": 4,
          "text": "도지캔들이 나오고 다시 이걸 던는 음본 캔들이 나오면"
        }
      ]
    },
    "wave_position": {
      "hits": 34,
      "summary": "파동/조정 위치 언급이 34회 잡혔습니다. 방향보다 현재 파동 위치 해석이 중요합니다.",
      "evidence": [
        {
          "time": "00:22:18",
          "start": 1338.16,
          "score": 6,
          "text": "380 끝나고 나오는 480 조정 후가 아니을 거잖아요. 그래서 480 조정에도 수익이 있고 그다음에 떨어진 ABC 반등 후"
        },
        {
          "time": "00:30:10",
          "start": 1810.26,
          "score": 4,
          "text": "좀 웃기죠 왜냐하면 여기 조정의 크기 대비 여기 조정의 크기를 비교해 보면"
        },
        {
          "time": "00:32:10",
          "start": 1930.43,
          "score": 4,
          "text": "WX와에 올라간다고 했었을 때 각각 이제 서파동이 또 이렇게 있잖아요 연예 서파동은 이제 가로그리"
        },
        {
          "time": "00:33:05",
          "start": 1985.0,
          "score": 11,
          "text": "중간 조정파동의 크기 중간의 크기와 여기 이 조정은 이 주황색 A에 대한 조정이고요 여기 ABC 조정"
        },
        {
          "time": "00:35:42",
          "start": 2142.39,
          "score": 6,
          "text": "그러면 이 자리구 6개파 자리가 또 마침 늘 공교롭게도 4파 조정이 있었던 맴을 때 자리에요"
        },
        {
          "time": "00:38:01",
          "start": 2281.14,
          "score": 4,
          "text": "그럼 조정은 오는 거면 진짜 자신이 이렇게 풀면서 우리 권했을 텐데 여기 조정이 좀 작아서"
        }
      ]
    }
  },
  "scenario_plan": {
    "entry_if": "지지/채널/저점 구조가 유지되고 눌림 후 반등 확인이 나올 때만 롱 후보로 본다.",
    "invalidated_if": "저점 또는 채널 하단이 깨지고 회복하지 못하면 롱 시나리오를 폐기한다.",
    "stop_logic": "손절선은 진입가가 아니라 시나리오가 틀렸다고 판단되는 구조선 기준으로 둔다.",
    "target_logic": "목표가는 다음 저항/지지 또는 파동 목표 부근에서 분할 청산하고 남은 물량은 추세 유지 여부로 관리한다.",
    "avoid_if": "손절 거리가 멀거나, 구조 확인 없이 단어 하나만으로 방향을 정해야 하는 구간은 피한다."
  },
  "algorithm_rules": [
    {
      "name": "structure_first",
      "rule": "방향 신호보다 지지/저항/채널/고점저점 구조 확인을 우선한다.",
      "reason": "차트 구조 히트 15회"
    },
    {
      "name": "stop_before_entry",
      "rule": "진입 전에 손절/무효화 가격을 먼저 계산하고, 손절 폭이 크면 거래하지 않는다.",
      "reason": "손절/무효화 히트 3회"
    },
    {
      "name": "conditional_aggression",
      "rule": "공격적 진입은 구조, 진입조건, 손절조건이 동시에 잡힌 ACTIONABLE 영상 패턴에서만 허용한다.",
      "reason": "현재 판정 ACTIONABLE"
    },
    {
      "name": "direction_bias",
      "rule": "이 영상은 LONG 우위 시나리오로 분류하되, 반대 구조 돌파/이탈 시 즉시 폐기한다.",
      "reason": "long=28, short=4"
    },
    {
      "name": "wave_filter",
      "rule": "파동 위치가 조정 중인지, 3파/5파 진행 중인지 확인한 뒤 진입 방향을 확정한다.",
      "reason": "파동/조정 히트 34회"
    }
  ],
  "quality_flags": [
    "기본 매매 판단 축이 모두 감지되었습니다."
  ]
}