{
  "schema": "maeuknam_decision_structure.v1",
  "id": "rs5svWWh0iA",
  "title": "[May 21, 2025] Bitcoin Analysis #BitcoinLiveBroadcast",
  "url": "https://www.youtube.com/watch?v=rs5svWWh0iA",
  "duration": 3582.2585,
  "model": "tiny",
  "bias": {
    "primary_bias": "LONG",
    "long_score": 10,
    "short_score": 2,
    "explanation": "롱/상승/반등 계열 표현이 숏/하락 표현보다 뚜렷하게 많습니다."
  },
  "trade_readiness": {
    "level": "ACTIONABLE",
    "score": 4,
    "reason": "구조, 진입, 손절이 함께 잡혀 있고 청산 또는 파동 필터까지 있어 실전 규칙 후보로 볼 수 있습니다."
  },
  "category_hits": {
    "market_context": 17,
    "direction_judgment": 8,
    "chart_structure": 13,
    "entry_trigger": 9,
    "stop_invalidation": 4,
    "take_profit_exit": 0,
    "timeframe": 0,
    "wave_position": 12
  },
  "sections": {
    "market_context": {
      "hits": 17,
      "summary": "시장 배경 언급이 17회 잡혔고, 대표 구간은 '그러면 이제 조금 더 차트가 비트코인과'입니다.",
      "evidence": [
        {
          "time": "00:24:51",
          "start": 1491.24,
          "score": 1,
          "text": "막에 폰들하고 그런 자금들"
        },
        {
          "time": "00:27:11",
          "start": 1631.62,
          "score": 2,
          "text": "그래서 실제로 금리 인상하겠다. 그래서 금리가 때 많이 올라왔죠."
        },
        {
          "time": "00:28:36",
          "start": 1716.91,
          "score": 3,
          "text": "그러면 이제 조금 더 차트가 비트코인과"
        },
        {
          "time": "00:32:11",
          "start": 1931.27,
          "score": 2,
          "text": "우리는 시장은 참 편여하다고 생각을 하고 있으니까 가격이 먼저 반영한 게"
        },
        {
          "time": "00:36:08",
          "start": 2168.87,
          "score": 2,
          "text": "좀 어려운 이야기긴 한데 근데 그런 것도 금리가 올라간 효과가 있으니까 이동성을 풀어서 또 금리를 내려 할 거다"
        },
        {
          "time": "00:51:42",
          "start": 3102.73,
          "score": 2,
          "text": "강전하겠습니다 딱 2만 달러 좀 놓으면 좋겠네요 수록과 2만 3천 달러"
        }
      ]
    },
    "direction_judgment": {
      "hits": 8,
      "summary": "방향 판단 언급이 8회 잡혔습니다. 핵심은 '신곡 좀 돌파를 한다면 돌파를 한다면 돌파 가게 나올 확률과' 구간입니다.",
      "evidence": [
        {
          "time": "00:18:46",
          "start": 1126.11,
          "score": 4,
          "text": "롱을 탄나 이런 또 자살 행장 여기서 롱을 어떻게 들어가냐"
        },
        {
          "time": "00:19:32",
          "start": 1172.27,
          "score": 3,
          "text": "이제 지지 받았잖아 지지어 골라할 거 생각을 했어 어 올라오네"
        },
        {
          "time": "00:21:34",
          "start": 1294.48,
          "score": 3,
          "text": "추경을 롱이라는 건 추세가"
        },
        {
          "time": "00:39:03",
          "start": 2343.34,
          "score": 6,
          "text": "신곡 좀 돌파를 한다면 돌파를 한다면 돌파 가게 나올 확률과"
        },
        {
          "time": "00:55:50",
          "start": 3350.44,
          "score": 4,
          "text": "여기서 롱을 어떻게 타이냐로. 아, 이 지인. 여기서 롱을 어떻게 타?"
        }
      ]
    },
    "chart_structure": {
      "hits": 13,
      "summary": "고점/저점, 지지/저항, 채널/라인 같은 구조 판단이 13회 잡혔습니다.",
      "evidence": [
        {
          "time": "00:12:55",
          "start": 775.02,
          "score": 6,
          "text": "고점 넘길 타이틀에 없겠다 고점이 낮아지고 있었는데 고점이 높아지는 부분을 하면"
        },
        {
          "time": "00:13:35",
          "start": 815.07,
          "score": 3,
          "text": "진입을 했고 그런데 고점을 한 번 더"
        },
        {
          "time": "00:16:38",
          "start": 998.9,
          "score": 4,
          "text": "손절라인 너무 짧지 않나 손절라인"
        },
        {
          "time": "00:19:17",
          "start": 1157.27,
          "score": 3,
          "text": "뭐 손절을 얻어졌을 건데 손절 라인 정말 수 없죠"
        },
        {
          "time": "00:19:31",
          "start": 1171.27,
          "score": 4,
          "text": "떨어질 수 있지 이제 지지 받았잖아 지지어 골라할 거 생각을 했어"
        },
        {
          "time": "00:39:03",
          "start": 2343.34,
          "score": 6,
          "text": "신곡 좀 돌파를 한다면 돌파를 한다면 돌파 가게 나올 확률과"
        }
      ]
    },
    "entry_trigger": {
      "hits": 9,
      "summary": "진입 조건은 추격보다 확인, 눌림, 반등, 돌파 여부 중심으로 9회 등장합니다.",
      "evidence": [
        {
          "time": "00:13:31",
          "start": 811.07,
          "score": 4,
          "text": "다시 여기에서 쇼스의 진입을 했습니다 진입을 했고"
        },
        {
          "time": "00:18:51",
          "start": 1131.16,
          "score": 4,
          "text": "여기서 롱을 어떻게 들어가냐 떨어지게 기다렸다가 출선이 여기서 롱 들어가서"
        },
        {
          "time": "00:21:38",
          "start": 1298.86,
          "score": 4,
          "text": "이전 저항받고 있는데 롱을 들어가는"
        },
        {
          "time": "00:39:03",
          "start": 2343.34,
          "score": 6,
          "text": "신곡 좀 돌파를 한다면 돌파를 한다면 돌파 가게 나올 확률과"
        }
      ]
    },
    "stop_invalidation": {
      "hits": 4,
      "summary": "손절/무효화 언급이 4회 잡혔습니다. 진입 전 리스크 위치를 먼저 보는 영상입니다.",
      "evidence": [
        {
          "time": "00:12:48",
          "start": 768.02,
          "score": 4,
          "text": "손절이야 한 입절 또는 반 손절이죠"
        },
        {
          "time": "00:16:38",
          "start": 998.9,
          "score": 4,
          "text": "손절라인 너무 짧지 않나 손절라인"
        },
        {
          "time": "00:19:17",
          "start": 1157.27,
          "score": 4,
          "text": "뭐 손절을 얻어졌을 건데 손절 라인 정말 수 없죠"
        },
        {
          "time": "00:46:49",
          "start": 2809.19,
          "score": 3,
          "text": "근데 이거 보나 많아 본절 나갈 것 같은데 스탄소스터저기 직전이네요 반익절 해놔서 딱 본절 정도 될 것 같아요"
        }
      ]
    },
    "take_profit_exit": {
      "hits": 0,
      "summary": "명확한 근거 구간이 부족합니다.",
      "evidence": []
    },
    "timeframe": {
      "hits": 0,
      "summary": "명확한 근거 구간이 부족합니다.",
      "evidence": []
    },
    "wave_position": {
      "hits": 12,
      "summary": "파동/조정 위치 언급이 12회 잡혔습니다. 방향보다 현재 파동 위치 해석이 중요합니다.",
      "evidence": [
        {
          "time": "00:19:11",
          "start": 1151.27,
          "score": 4,
          "text": "그러면 제가 불구하고 롱 진입은 언제? 조정끝대"
        },
        {
          "time": "00:39:07",
          "start": 2347.42,
          "score": 4,
          "text": "돌파 가게 나올 확률과 돌파와 배캐의 뭔가에 다시 떨어졌다가 조정을 바꿔가는 진애를 좀"
        },
        {
          "time": "00:53:24",
          "start": 3204.5,
          "score": 7,
          "text": "또 불규칙의 연장파동이야 그럼 또 이게 결국에는 에위 씨 없고 또 연장파동 1파동 낙고 입화동 낙고"
        },
        {
          "time": "00:54:08",
          "start": 3248.3,
          "score": 4,
          "text": "뭐? 오파동 연장이 됐는데 오해, 오갖도 안장파동 봐야 돼"
        },
        {
          "time": "00:56:41",
          "start": 3401.86,
          "score": 6,
          "text": "한 시간 뒤에 계신 된다고 하더라도 추격 탐의로는 없어요. 차분히 조정 기다렸다가 그리고 나서 조정파동의 현물도 들어갈 거고"
        },
        {
          "time": "00:58:54",
          "start": 3534.3,
          "score": 4,
          "text": "아쉽지만 조정 택까지는 너무 아쉬운 마음으로 조정의 오기를 좀 기다려 보겠습니다."
        }
      ]
    }
  },
  "scenario_plan": {
    "entry_if": "지지/채널/저점 구조가 유지되고 눌림 후 반등 확인이 나올 때만 롱 후보로 본다.",
    "invalidated_if": "저점 또는 채널 하단이 깨지고 회복하지 못하면 롱 시나리오를 폐기한다.",
    "stop_logic": "손절선은 진입가가 아니라 시나리오가 틀렸다고 판단되는 구조선 기준으로 둔다.",
    "target_logic": "직접적인 익절 언급은 약하므로 파동 목표와 다음 구조선을 임시 목표로만 쓰고, 별도 차트 검증 전에는 거래하지 않는다.",
    "avoid_if": "손절 거리가 멀거나, 구조 확인 없이 단어 하나만으로 방향을 정해야 하는 구간은 피한다."
  },
  "algorithm_rules": [
    {
      "name": "structure_first",
      "rule": "방향 신호보다 지지/저항/채널/고점저점 구조 확인을 우선한다.",
      "reason": "차트 구조 히트 13회"
    },
    {
      "name": "stop_before_entry",
      "rule": "진입 전에 손절/무효화 가격을 먼저 계산하고, 손절 폭이 크면 거래하지 않는다.",
      "reason": "손절/무효화 히트 4회"
    },
    {
      "name": "conditional_aggression",
      "rule": "공격적 진입은 구조, 진입조건, 손절조건이 동시에 잡힌 ACTIONABLE 영상 패턴에서만 허용한다.",
      "reason": "현재 판정 ACTIONABLE"
    },
    {
      "name": "direction_bias",
      "rule": "이 영상은 LONG 우위 시나리오로 분류하되, 반대 구조 돌파/이탈 시 즉시 폐기한다.",
      "reason": "long=10, short=2"
    },
    {
      "name": "wave_filter",
      "rule": "파동 위치가 조정 중인지, 3파/5파 진행 중인지 확인한 뒤 진입 방향을 확정한다.",
      "reason": "파동/조정 히트 12회"
    }
  ],
  "quality_flags": [
    "시간 프레임이 명확하지 않습니다."
  ]
}