{
  "schema": "maeuknam_decision_structure.v1",
  "id": "yDF-P25bR5c",
  "title": "[2024.11.06]매억남_비트코인 분석방송 #비트코인 #bitcoin #btc #chart analysis",
  "url": "https://www.youtube.com/watch?v=yDF-P25bR5c",
  "duration": 4052.8573125,
  "model": "tiny",
  "bias": {
    "primary_bias": "LONG",
    "long_score": 4,
    "short_score": 0,
    "explanation": "롱/상승/반등 계열 표현이 숏/하락 표현보다 뚜렷하게 많습니다."
  },
  "trade_readiness": {
    "level": "CONDITIONAL",
    "score": 3,
    "reason": "일부 조건은 잡히지만 빠진 축이 있어 차트 프레임 확인 후 규칙화해야 합니다."
  },
  "category_hits": {
    "market_context": 6,
    "direction_judgment": 4,
    "chart_structure": 4,
    "entry_trigger": 2,
    "stop_invalidation": 0,
    "take_profit_exit": 1,
    "timeframe": 1,
    "wave_position": 5
  },
  "sections": {
    "market_context": {
      "hits": 6,
      "summary": "시장 배경 언급이 6회 잡혔고, 대표 구간은 '나올 거라고 생각하고 있습니다. 지금 비트코인이 신고점을 찍어서 한 얘기가 아니라 이 장기관점은'입니다.",
      "evidence": [
        {
          "time": "00:20:39",
          "start": 1239.58,
          "score": 2,
          "text": "그리고 떨어지지 않을까 그러니까 지금 생각입니다. 그리고 장기관점에서 봤을 때"
        },
        {
          "time": "00:21:45",
          "start": 1305.82,
          "score": 4,
          "text": "나올 거라고 생각하고 있습니다. 지금 비트코인이 신고점을 찍어서 한 얘기가 아니라 이 장기관점은"
        },
        {
          "time": "00:27:49",
          "start": 1669.34,
          "score": 1,
          "text": "이때 이미 비트 살살한 다사고 행복하기 때문에 비트 보다는 시장이 좋은데"
        },
        {
          "time": "00:31:54",
          "start": 1914.08,
          "score": 1,
          "text": "이런 팔아 볼까 이제 좀 팔아 볼까 시장 분위기에 바가면서"
        }
      ]
    },
    "direction_judgment": {
      "hits": 4,
      "summary": "방향 판단 언급이 4회 잡혔습니다. 핵심은 '옆금 계속 치켜보고 있었던 것 같습니다. 최근에 하나 아쉬웠던 거는 이때가 롱잘이었는데 아 이롱잘이를 들어갈까 말까를 고면 했는데' 구간입니다.",
      "evidence": [
        {
          "time": "00:12:47",
          "start": 767.57,
          "score": 4,
          "text": "옆금 계속 치켜보고 있었던 것 같습니다. 최근에 하나 아쉬웠던 거는 이때가 롱잘이었는데 아 이롱잘이를 들어갈까 말까를 고면 했는데"
        },
        {
          "time": "00:17:03",
          "start": 1023.85,
          "score": 3,
          "text": "여기 구간 구간을 인퍼도록 볼 수 있겠습니다만. 그래도 전반적인 하동이 원투엄 두 같지도 않고 ABC로 올라가고 있는 것 같아요."
        },
        {
          "time": "00:18:49",
          "start": 1129.85,
          "score": 4,
          "text": "많이 올라갔으면 첫 파도 아래사이가 감해스러 많이 올라오고 조정 이후에 올랐지만 조정이 올랐으니까"
        },
        {
          "time": "00:20:19",
          "start": 1219.5,
          "score": 4,
          "text": "올라간다면 그리고 조정이 오고 또 오르고 조정이 오고 또 올라서 이런 식으로 엔딩이 나오면"
        },
        {
          "time": "00:23:57",
          "start": 1437.4,
          "score": 3,
          "text": "타점이 없습니다. 타점이 없어서 맘매는 안 할 생각이 듭니다. 꾸준히 더 올라서 엔딩"
        },
        {
          "time": "00:37:15",
          "start": 2235.72,
          "score": 3,
          "text": "이렇게 AVC 모양으로 올라오게 되면 이제 연장파동이 생긴다는 거예요 이런 식으로 그래서 이런 식으로 연장파동 생기면"
        }
      ]
    },
    "chart_structure": {
      "hits": 4,
      "summary": "고점/저점, 지지/저항, 채널/라인 같은 구조 판단이 4회 잡혔습니다.",
      "evidence": [
        {
          "time": "00:16:54",
          "start": 1014.69,
          "score": 4,
          "text": "지금 저점이 여기 나왔었고 그 뒤로 첫 하동도 ABC 나왔고 여기 구간 구간을 인퍼도록 볼 수 있겠습니다만."
        },
        {
          "time": "00:21:43",
          "start": 1303.02,
          "score": 3,
          "text": "대략한 하나로 1억 8천에서 2억 선까지 나올 거라고 생각하고 있습니다. 지금 비트코인이 신고점을 찍어서"
        },
        {
          "time": "00:27:42",
          "start": 1662.54,
          "score": 3,
          "text": "어느 정도 당연히 비트가 고점에서 행복하면서 뭐 잘 지켜주는 가격을 방어를 해주면"
        },
        {
          "time": "00:28:36",
          "start": 1716.86,
          "score": 4,
          "text": "내가 지금 비트 코인 신고점 역사적 신고점"
        }
      ]
    },
    "entry_trigger": {
      "hits": 2,
      "summary": "진입 조건은 추격보다 확인, 눌림, 반등, 돌파 여부 중심으로 2회 등장합니다.",
      "evidence": [
        {
          "time": "00:23:55",
          "start": 1435.4,
          "score": 4,
          "text": "지금 맘매할 타점이 없습니다. 타점이 없어서 맘매는 안 할 생각이 듭니다."
        }
      ]
    },
    "stop_invalidation": {
      "hits": 0,
      "summary": "명확한 근거 구간이 부족합니다.",
      "evidence": []
    },
    "take_profit_exit": {
      "hits": 1,
      "summary": "수익 실현/청산 언급이 1회 잡혔습니다. 목표 도달 후 분할 또는 정리 맥락을 확인해야 합니다.",
      "evidence": [
        {
          "time": "00:18:52",
          "start": 1132.57,
          "score": 3,
          "text": "아래사이가 감해스러 많이 올라오고 조정 이후에 올랐지만 조정이 올랐으니까 대변스가 먹고"
        }
      ]
    },
    "timeframe": {
      "hits": 1,
      "summary": "분봉/시간봉/일봉 등 시간 프레임 언급이 1회 잡혔습니다.",
      "evidence": [
        {
          "time": "00:21:45",
          "start": 1305.82,
          "score": 3,
          "text": "나올 거라고 생각하고 있습니다. 지금 비트코인이 신고점을 찍어서 한 얘기가 아니라 이 장기관점은"
        }
      ]
    },
    "wave_position": {
      "hits": 5,
      "summary": "파동/조정 위치 언급이 5회 잡혔습니다. 방향보다 현재 파동 위치 해석이 중요합니다.",
      "evidence": [
        {
          "time": "00:16:54",
          "start": 1014.69,
          "score": 4,
          "text": "지금 저점이 여기 나왔었고 그 뒤로 첫 하동도 ABC 나왔고 여기 구간 구간을 인퍼도록 볼 수 있겠습니다만."
        },
        {
          "time": "00:18:49",
          "start": 1129.85,
          "score": 4,
          "text": "많이 올라갔으면 첫 파도 아래사이가 감해스러 많이 올라오고 조정 이후에 올랐지만 조정이 올랐으니까"
        },
        {
          "time": "00:20:19",
          "start": 1219.5,
          "score": 4,
          "text": "올라간다면 그리고 조정이 오고 또 오르고 조정이 오고 또 올라서 이런 식으로 엔딩이 나오면"
        },
        {
          "time": "00:37:00",
          "start": 2220.84,
          "score": 4,
          "text": "엔딩이랑 말 그대로 끝나는 파동을 의미하고 마지막에 이제 이런 식으로 파동이"
        }
      ]
    }
  },
  "scenario_plan": {
    "entry_if": "지지/채널/저점 구조가 유지되고 눌림 후 반등 확인이 나올 때만 롱 후보로 본다.",
    "invalidated_if": "저점 또는 채널 하단이 깨지고 회복하지 못하면 롱 시나리오를 폐기한다.",
    "stop_logic": "손절 근거가 부족하므로 별도 차트 검증 없이는 진입하지 않는다.",
    "target_logic": "직접적인 익절 언급은 약하므로 파동 목표와 다음 구조선을 임시 목표로만 쓰고, 별도 차트 검증 전에는 거래하지 않는다.",
    "avoid_if": "손절 거리가 멀거나, 구조 확인 없이 단어 하나만으로 방향을 정해야 하는 구간은 피한다."
  },
  "algorithm_rules": [
    {
      "name": "structure_first",
      "rule": "방향 신호보다 지지/저항/채널/고점저점 구조 확인을 우선한다.",
      "reason": "차트 구조 히트 4회"
    },
    {
      "name": "stop_before_entry",
      "rule": "진입 전에 손절/무효화 가격을 먼저 계산하고, 손절 폭이 크면 거래하지 않는다.",
      "reason": "손절/무효화 히트 0회"
    },
    {
      "name": "conditional_aggression",
      "rule": "공격적 진입은 구조, 진입조건, 손절조건이 동시에 잡힌 ACTIONABLE 영상 패턴에서만 허용한다.",
      "reason": "현재 판정 CONDITIONAL"
    },
    {
      "name": "direction_bias",
      "rule": "이 영상은 LONG 우위 시나리오로 분류하되, 반대 구조 돌파/이탈 시 즉시 폐기한다.",
      "reason": "long=4, short=0"
    },
    {
      "name": "wave_filter",
      "rule": "파동 위치가 조정 중인지, 3파/5파 진행 중인지 확인한 뒤 진입 방향을 확정한다.",
      "reason": "파동/조정 히트 5회"
    }
  ],
  "quality_flags": [
    "손절/무효화 조건 근거가 부족합니다."
  ]
}